LICENSE
MANIFEST.in
README.md
setup.py
tox.ini
django_tarview.egg-info/PKG-INFO
django_tarview.egg-info/SOURCES.txt
django_tarview.egg-info/dependency_links.txt
django_tarview.egg-info/top_level.txt
tarview/__init__.py
tarview/test_settings.py
tarview/views.py