Metadata-Version: 1.1
Name: django-tarview
Version: 1.0.0
Summary: A simple Django base view to tar and stream several files.
Home-page: https://github.com/luckydonald/django-tarview/
Author: luckydonald
Author-email: code@luckydonald.de
License: MIT License
Platform: UNKNOWN
Classifier: Environment :: Web Environment
Classifier: Framework :: Django
Classifier: Intended Audience :: Developers
Classifier: License :: OSI Approved :: MIT License
Classifier: Operating System :: OS Independent
Classifier: Programming Language :: Python
Classifier: Programming Language :: Python :: 3
Classifier: Programming Language :: Python :: 3.3
Classifier: Topic :: Internet :: WWW/HTTP
Classifier: Topic :: Internet :: WWW/HTTP :: Dynamic Content
